aimfast/__init__.py
aimfast/aimfast.py
aimfast/auxiliary.py
aimfast/main.py
aimfast/source_finder.yml
aimfast/tests/__init__.py
aimfast/tests/files/DR_catalog.txt
aimfast/tests/files/catalog.lsm.html
aimfast/tests/files/catalog1.lsm.html
aimfast/tests/files/catalog1.txt
aimfast/tests/files/cube1.fits
aimfast/tests/files/cube2.fits
aimfast/tests/files/fidelity_results.json
aimfast/tests/files/mask.fits
aimfast/tests/test_aimfast.py
aimfast-1.3.4.dist-info/LICENSE
aimfast-1.3.4.dist-info/METADATA
aimfast-1.3.4.dist-info/WHEEL
aimfast-1.3.4.dist-info/entry_points.txt
aimfast-1.3.4.dist-info/RECORD
