Metadata-Version: 2.1
Name: aimfast
Version: 1.3.4
Summary: An Astronomical Image Fidelity Assessment Tool.
Home-page: https://github.com/Athanaseus/aimfast
License: GNU GPL 3
Keywords: fits,dataset,lsm,models,statistics,html,catalogs
Author: Athanaseus Ramaila
Author-email: ramaila.jat@gmail.com
Requires-Python: >=3.8
Classifier: Development Status :: 5 - Production/Stable
Classifier: Intended Audience :: Science/Research
Classifier: License :: OSI Approved :: GNU General Public License v3 (GPLv3)
Classifier: License :: Other/Proprietary License
Classifier: Programming Language :: Python :: 3
Classifier: Programming Language :: Python :: 3.8
Classifier: Programming Language :: Python :: 3.9
Classifier: Programming Language :: Python :: 3.10
Classifier: Programming Language :: Python :: 3.11
Classifier: Programming Language :: Python :: 3.8
Classifier: Topic :: Scientific/Engineering :: Astronomy
Classifier: Topic :: Software Development :: Libraries
Provides-Extra: aegean
Provides-Extra: doc
Provides-Extra: pybdsf
Provides-Extra: source-finders
Provides-Extra: svg-images
Provides-Extra: testing
Requires-Dist: AegeanTools ; extra == "aegean" or extra == "source-finders"
Requires-Dist: astLib (==0.10.0)
Requires-Dist: astro-tigger
Requires-Dist: astropy
Requires-Dist: astroquery
Requires-Dist: bdsf ; extra == "pybdsf" or extra == "source-finders"
Requires-Dist: bokeh
Requires-Dist: jsonschema
Requires-Dist: matplotlib ; extra == "pybdsf" or extra == "source-finders" or extra == "svg-images"
Requires-Dist: mock
Requires-Dist: numpy
Requires-Dist: numpydoc ; extra == "doc"
Requires-Dist: pytest (>=7.2.2,<8.0.0) ; extra == "testing"
Requires-Dist: pytest-flake8 (>=1.1.1,<2.0.0) ; extra == "testing"
Requires-Dist: pyyaml
Requires-Dist: regions
Requires-Dist: scikit-learn
Requires-Dist: scipy
Requires-Dist: selenium ; extra == "svg-images"
Project-URL: Repository, https://github.com/Athanaseus/aimfast.git
